_wenet.cpython-39-x86_64-linux-gnu.so
libwenet_api.so
wenetrt/__init__.py
wenetrt/decoder.py
wenetrt/hub.py
wenetrt-1.0.9.dist-info/METADATA
wenetrt-1.0.9.dist-info/WHEEL
wenetrt-1.0.9.dist-info/top_level.txt
wenetrt-1.0.9.dist-info/RECORD
