Metadata-Version: 2.1
Name: wenetrt
Version: 1.0.9
Summary: UNKNOWN
Home-page: https://github.com/wenet-e2e/wenet
Author: Zhendong Peng
Author-email: 275331498@qq.com
License: Apache licensed, as found in the LICENSE file
Platform: UNKNOWN
Classifier: Programming Language :: C++
Classifier: Programming Language :: Python :: 3
Classifier: Operating System :: OS Independent
Classifier: Topic :: Scientific/Engineering :: Artificial Intelligence
Requires-Dist: torch
Requires-Dist: tqdm
